nbinteract/__init__.py
nbinteract/cli.py
nbinteract/exporters.py
nbinteract/plotting.py
nbinteract/preprocessors.py
nbinteract/questions.py
nbinteract/util.py
nbinteract/templates/full.tpl
nbinteract/templates/local.tpl
nbinteract/templates/nbinteract_css.tpl
nbinteract/templates/partial.tpl
nbinteract/templates/plain.tpl
nbinteract-0.2.4.dist-info/LICENSE.txt
nbinteract-0.2.4.dist-info/METADATA
nbinteract-0.2.4.dist-info/WHEEL
nbinteract-0.2.4.dist-info/entry_points.txt
nbinteract-0.2.4.dist-info/top_level.txt
nbinteract-0.2.4.dist-info/RECORD
