Metadata-Version: 2.1
Name: nbinteract
Version: 0.2.4
Summary: Export interactive HTML pages from Jupyter Notebooks
Home-page: https://github.com/SamLau95/nbinteract
Author: Sam Lau
Author-email: samlau95@gmail.com
License: MIT
Keywords: jupyter nbconvert interact
Platform: UNKNOWN
Classifier: Development Status :: 3 - Alpha
Classifier: Intended Audience :: Developers
Classifier: Topic :: Software Development :: Build Tools
Classifier: License :: OSI Approved :: MIT License
Classifier: Programming Language :: Python :: 3
Classifier: Programming Language :: Python :: 3.3
Classifier: Programming Language :: Python :: 3.4
Classifier: Programming Language :: Python :: 3.5
Classifier: Framework :: Jupyter
Requires-Dist: numpy (<2,>=1)
Requires-Dist: IPython (<8,>=6)
Requires-Dist: nbconvert (<6,>=5.3)
Requires-Dist: traitlets (<5,>=4.3)
Requires-Dist: bqplot (<1,>=0.10)
Requires-Dist: ipywidgets (<8,>=7)
Requires-Dist: toolz (<1,>=0.8)
Requires-Dist: docopt (<1,>=0.6.2)
Requires-Dist: nbformat (<5,>=4.4.0)
Requires-Dist: Jinja2 (<3,>=2.10)
Provides-Extra: dev
Requires-Dist: check-manifest ; extra == 'dev'
Provides-Extra: test
Requires-Dist: pytest ; extra == 'test'
Requires-Dist: coverage ; extra == 'test'
Requires-Dist: coveralls ; extra == 'test'
